DS18B20_driver/DS18B20.py
DS18B20_driver/__init__.py
DS18B20_driver-1.1.2.dist-info/LICENSE.txt
DS18B20_driver-1.1.2.dist-info/METADATA
DS18B20_driver-1.1.2.dist-info/WHEEL
DS18B20_driver-1.1.2.dist-info/entry_points.txt
DS18B20_driver-1.1.2.dist-info/top_level.txt
DS18B20_driver-1.1.2.dist-info/RECORD
