Metadata-Version: 2.1
Name: DS18B20-driver
Version: 1.1.2
Summary: DS18B20 library/driver for Raspberry Pi using the w1_therm kernel driver
Author-email: Chris Nelson <github@cjnaz.com>
License: MIT License
Project-URL: repository, https://github.com/cjnaz/DS18B20
Classifier: Topic :: Software Development :: Libraries :: Python Modules
Requires-Python: >=3.7
License-File: LICENSE.txt
